saml2idp/__init__.py
saml2idp/base.py
saml2idp/codex.py
saml2idp/demo.py
saml2idp/exceptions.py
saml2idp/google_apps.py
saml2idp/logging.py
saml2idp/metadata.py
saml2idp/models.py
saml2idp/registry.py
saml2idp/salesforce.py
saml2idp/saml2idp_metadata.py
saml2idp/shib.py
saml2idp/urls.py
saml2idp/utils.py
saml2idp/views.py
saml2idp/xml_render.py
saml2idp/xml_signing.py
saml2idp/xml_templates.py
saml2idp/templates/saml2idp/base.html
saml2idp/templates/saml2idp/idpssodescriptor.xml
saml2idp/templates/saml2idp/invalid_user.html
saml2idp/templates/saml2idp/logged_out.html
saml2idp/templates/saml2idp/login.html
dj_saml_idp-1.2.1.dist-info/LICENSE
dj_saml_idp-1.2.1.dist-info/METADATA
dj_saml_idp-1.2.1.dist-info/WHEEL
dj_saml_idp-1.2.1.dist-info/top_level.txt
dj_saml_idp-1.2.1.dist-info/RECORD
