Metadata-Version: 2.1
Name: dj-saml-idp
Version: 1.2.1
Summary: SAML 2.0 IdP for Django
Home-page: http://github.com/mobify/dj-saml-idp
Author: Sebastian Vetter
Author-email: sebastian@mobify.com
License: MIT
Platform: UNKNOWN
Requires-Dist: Django (<2)
Requires-Dist: M2Crypto (>=0.35.2)
Requires-Dist: beautifulsoup4 (>=4.8.1)
Requires-Dist: lxml (==4.4.1)
Requires-Dist: structlog (==16.1.0)
